{
  "GameObject": [
    {
      "Component": {
        "Transform": [
          [ 0.9728866219520569, -3.4924596548080444e-10, -0.231282576918602, 0.0 ],
          [ 0.13493148982524872, 0.8121813535690308, 0.5675867795944214, 0.0 ],
          [ 0.187843456864357, -0.5834047794342041, 0.7901603579521179, 0.0 ],
          [ 0.0, 10.0, -10.0, 1.0 ]
        ]
      },

      "Desc": {
        "Type": 
      }

      "Hash": 8675365520207489377,
      "Name": "class Client::CCamera_Free",
      "Setting": { "Enable": true }
    },
    {
      "Component": {
        "Transform": [
          [ 1.0, 0.0, 0.0, 0.0 ],
          [ 0.0, 1.0, 0.0, 0.0 ],
          [ 0.0, 0.0, 1.0, 0.0 ],
          [ 0.0, 0.0, 0.0, 1.0 ]
        ]
      },
      "Hash": 3297996505304094455,
      "Name": "class Client::CTerrain",
      "Setting": { "Enable": true }
    },
    {
      "Component": { "Transform": { "": null } },
      "Hash": 9630067207881014080,
      "Name": "class Client::CEditSetActor",
      "Setting": { "Enable": true }
    },
    {
      "Component": {
        "Model": "Mon_AxeMan",
        "Transform": [
          [ 1.0, 0.0, 0.0, 0.0 ],
          [ 0.0, 1.0, 7.867813110351563e-06, 0.0 ],
          [ 0.0, -7.867813110351563e-06, 1.0, 0.0 ],
          [ 6.42288875579834, 0.0, 17.368711471557617, 1.0 ]
        ]
      },
      "Hash": 12933828336327676828,
      "Name": "class Client::CNorMonster",
      "Setting": { "Enable": true }
    }
  ]
}
